Workbook

Sheet 📊 Dashboard
A1: 🏦 FinTrack Panama — Panel de Control
A2: Actualizado: 06/04/2026
A4: 💰 RESUMEN DE INGRESOS | C4: 🏦 DEUDAS TOTALES
A5: Salario Bruto (quincenal) | B5: =IFERROR(AVERAGE('💰 Quincenas'!C:C),0) | C5: Total Deudas Pendientes | D5: =IFERROR(SUMIF('💳 Deudas'!G2:G500,"No",'💳 Deudas'!E2:E500),0)
A6: Deducción CSS (9.75%) | B6: =IFERROR(AVERAGE('💰 Quincenas'!D:D),0) | C6: Pago Mensual Total | D6: =IFERROR(SUMIF('💳 Deudas'!G2:G500,"No",'💳 Deudas'!F2:F500),0)
A7: Deducción Educativo (1.25%) | B7: =IFERROR(AVERAGE('💰 Quincenas'!E:E),0) | C7: Número de Deudas | D7: =IFERROR(COUNTIF('💳 Deudas'!G2:G500,"No"),0)
A8: Salario Neto (quincenal) | B8: =IFERROR(AVERAGE('💰 Quincenas'!F:F),0)
A9: Salario Neto (mensual) | B9: =IFERROR(AVERAGE('💰 Quincenas'!F:F)*2,0) | C9: 🎯 METAS DE AHORRO
C10: Meta Principal (objetivo) | D10: =IFERROR(MAXIFS('🎯 Ahorros'!C2:C500,'🎯 Ahorros'!F2:F500,"Sí"),0)
A11: 💸 RESUMEN DE GASTOS | C11: Ahorro Acumulado Total | D11: =IFERROR(SUM('🎯 Ahorros'!D2:D500),0)
A12: Total Gastos (este mes) | B12: =IFERROR(SUMPRODUCT(('💸 Gastos'!B2:B500<>"")*('💸 Gastos'!D2:D500)),0) | C12: % Alcanzado (meta princ.) | D12: =IFERROR(D11/D10,0)
A13: Gastos Fijos | B13: =IFERROR(SUMIF('💸 Gastos'!E2:E500,"FIJO",'💸 Gastos'!D2:D500),0)
A14: Gastos Variables | B14: =IFERROR(SUMIF('💸 Gastos'!E2:E500,"VARIABLE",'💸 Gastos'!D2:D500),0)
A15: Balance (Neto - Gastos) | B15: =B9-B13
A18: ℹ️ Todos los cálculos se actualizan automáticamente al ingresar datos en las otras hojas.

Sheet 💰 Quincenas
A1: 💰 Registro de Quincenas — FinTrack Panama
A2: Período | B2: Fecha Pago | C2: Salario Bruto | D2: CSS (9.75%) | E2: Educativo (1.25%) | F2: IFARHU (0.5%) | G2: Otras Deduc. | H2: Salario Neto | I2: Incluye IFARHU | J2: Notas
A3: 1ra Quincena Enero 2026 | B3: 15/01/2026 | C3: 900 | D3: =C3*0.0975 | E3: =C3*0.0125 | F3: =IF(I3="Sí",C3*0.005,0) | G3: 0 | H3: =C3-D3-E3-F3-G3 | I3: No
A4: 2da Quincena Enero 2026 | B4: 31/01/2026 | C4: 900 | D4: =C4*0.0975 | E4: =C4*0.0125 | F4: =IF(I4="Sí",C4*0.005,0) | G4: 0 | H4: =C4-D4-E4-F4-G4 | I4: No
A5: 1ra Quincena Feb 2026 | B5: 15/02/2026 | C5: 900 | D5: =C5*0.0975 | E5: =C5*0.0125 | F5: =IF(I5="Sí",C5*0.005,0) | G5: 0 | H5: =C5-D5-E5-F5-G5 | I5: No
A6: 2da Quincena Feb 2026 | B6: 28/02/2026 | C6: 900 | D6: =C6*0.0975 | E6: =C6*0.0125 | F6: =IF(I6="Sí",C6*0.005,0) | G6: 0 | H6: =C6-D6-E6-F6-G6 | I6: No
A7: TOTALES | C7: =SUM(C3:C6) | D7: =SUM(D3:D6) | E7: =SUM(E3:E6) | F7: =SUM(F3:F6) | G7: =SUM(G3:G6) | H7: =SUM(H3:H6)

Sheet 💸 Gastos
A1: 💸 Registro de Gastos — FinTrack Panama
A2: Fecha | B2: Descripción | C2: Categoría | D2: Monto | E2: Tipo | F2: Quincena | G2: Notas
A3: 05/04/2026 | B3: Supermercado El Rey | C3: ALIMENTACION | D3: 120 | E3: FIJO | F3: 1ra Quincena Abril
A4: 06/04/2026 | B4: Metro y autobús | C4: TRANSPORTE | D4: 45 | E4: VARIABLE | F4: 1ra Quincena Abril
A5: 07/04/2026 | B5: Cable + Internet | C5: SERVICIOS | D5: 80 | E5: FIJO | F5: 1ra Quincena Abril
A6: 08/04/2026 | B6: Farmacia Arrocha | C6: SALUD | D6: 30 | E6: VARIABLE | F6: 1ra Quincena Abril
A7: 09/04/2026 | B7: Netflix + Spotify | C7: ENTRETENIMIENTO | D7: 25 | E7: FIJO | F7: 1ra Quincena Abril
A8: TOTAL GASTOS | D8: =SUM(D3:D7)
A10: RESUMEN POR CATEGORÍA
A11: Categoría | B11: Total | C11: % del Total
A12: ALIMENTACION | B12: =SUMIF(C3:C7,A12,D3:D7) | C12: =IFERROR(B12/D8,0)
A13: TRANSPORTE | B13: =SUMIF(C3:C7,A13,D3:D7) | C13: =IFERROR(B13/D8,0)
A14: SALUD | B14: =SUMIF(C3:C7,A14,D3:D7) | C14: =IFERROR(B14/D8,0)
A15: ENTRETENIMIENTO | B15: =SUMIF(C3:C7,A15,D3:D7) | C15: =IFERROR(B15/D8,0)
A16: SERVICIOS | B16: =SUMIF(C3:C7,A16,D3:D7) | C16: =IFERROR(B16/D8,0)
A17: EDUCACION | B17: =SUMIF(C3:C7,A17,D3:D7) | C17: =IFERROR(B17/D8,0)
A18: VIVIENDA | B18: =SUMIF(C3:C7,A18,D3:D7) | C18: =IFERROR(B18/D8,0)
A19: ROPA | B19: =SUMIF(C3:C7,A19,D3:D7) | C19: =IFERROR(B19/D8,0)
A20: TECNOLOGIA | B20: =SUMIF(C3:C7,A20,D3:D7) | C20: =IFERROR(B20/D8,0)
A21: OTROS | B21: =SUMIF(C3:C7,A21,D3:D7) | C21: =IFERROR(B21/D8,0)

Sheet 💳 Deudas
A1: 💳 Registro de Deudas — FinTrack Panama
A2: Acreedor | B2: Fecha Inicio | C2: Monto Total | D2: Saldo Restante | E2: Monto Original | F2: Pago Mensual | G2: ¿Pagada? | H2: Tasa Interés | I2: Fecha Fin | J2: Notas
A3: Banco General | B3: 01/06/2023 | C3: 5000 | D3: 3200 | E3: 5000 | F3: 200 | G3: No | H3: 18% | I3: 01/06/2026 | J3: Préstamo personal
A4: TOTAL SALDO PENDIENTE | D4: =SUMIF(G3:G3,"No",D3:D3)

Sheet 🎯 Ahorros
A1: 🎯 Metas de Ahorro — FinTrack Panama
A2: Meta | B2: Fecha Límite | C2: Objetivo ($) | D2: Acumulado ($) | E2: % Alcanzado | F2: ¿Principal? | G2: ¿Completada? | H2: Notas
A3: Fondo de emergencia | B3: 31/12/2026 | C3: 3000 | D3: 750 | E3: =IFERROR(D3/C3,0) | F3: Sí | G3: No | H3: Meta principal
A4: Vacaciones en Colombia | B4: 15/08/2026 | C4: 1500 | D4: 300 | E4: =IFERROR(D4/C4,0) | F4: No | G4: No

Sheet 🏛️ Cuentas
A1: 🏛️ Cuentas Bancarias — FinTrack Panama
A2: Banco | B2: Tipo | C2: Alias | D2: Saldo ($) | E2: Moneda | F2: ¿Principal? | G2: ¿Activa? | H2: Notas
A3: Banco General | B3: AHORROS | C3: Mi cuenta principal | D3: 1500 | E3: USD | F3: Sí | G3: Sí
A4: Banistmo | B4: CORRIENTE | C4: Nómina | D4: 200 | E4: USD | F4: No | G4: Sí
A5: TOTAL ACTIVOS | D5: =SUMIF(G3:G4,"Sí",D3:D4)

Sheet 📋 Instrucciones
A1: 📋 Instrucciones de Uso — FinTrack Panama
A2: 📊 DASHBOARD | B2: Se actualiza solo. No editar esta hoja.
A3: 💰 QUINCENAS | B3: Ingresa tu salario bruto. CSS, Educativo e IFARHU se calculan automáticamente.
A4: 💸 GASTOS | B4: Registra cada gasto con fecha, descripción, categoría y tipo (FIJO/VARIABLE).
A5: 💳 DEUDAS | B5: Una fila por deuda. Actualiza el 'Saldo Restante' cada mes.
A6: 🎯 AHORROS | B6: Una fila por meta. Actualiza el 'Acumulado ($)' cuando ahorres.
A7: 🏛️ CUENTAS | B7: Registra tus cuentas bancarias y actualiza el saldo periódicamente.
A9: 🔢 FÓRMULAS CLAVE
A10: Salario Neto | B10: =Bruto − CSS(9.75%) − Educativo(1.25%) − IFARHU(0.5% si aplica)
A11: Balance mensual | B11: =Salario Neto × 2 − Total Gastos del mes
A12: % Meta de ahorro | B12: =Acumulado ÷ Objetivo
A14: 💡 CONSEJOS
A15: Actualización | B15: Actualiza el archivo cada quincena al recibir tu pago.
A16: Gastos | B16: Registra gastos apenas los hagas para no olvidarlos.
A17: Deudas | B17: Revisa el saldo de deudas una vez al mes.
A18: Ahorros | B18: Transfiere a ahorro primero antes de gastar (págate a ti mismo).
